dolphin_mcp/__init__.py
dolphin_mcp/cli.py
dolphin_mcp/client.py
dolphin_mcp/reasoning.py
dolphin_mcp/utils.py
dolphin_mcp/providers/__init__.py
dolphin_mcp/providers/anthropic.py
dolphin_mcp/providers/lmstudio.py
dolphin_mcp/providers/msazureopenai.py
dolphin_mcp/providers/ollama.py
dolphin_mcp/providers/openai.py
amitysolutions_dolphin_mcp-0.2.21.dist-info/METADATA
amitysolutions_dolphin_mcp-0.2.21.dist-info/WHEEL
amitysolutions_dolphin_mcp-0.2.21.dist-info/entry_points.txt
amitysolutions_dolphin_mcp-0.2.21.dist-info/top_level.txt
amitysolutions_dolphin_mcp-0.2.21.dist-info/RECORD
