Metadata-Version: 2.4
Name: amitysolutions.dolphin-mcp
Version: 0.2.21
Summary: A flexible Python client for interacting with Model Context Protocol (MCP) servers
Author: Dolphin MCP Team, Amity Team
License: MIT
Classifier: Programming Language :: Python :: 3
Classifier: License :: OSI Approved :: MIT License
Classifier: Operating System :: OS Independent
Requires-Python: >=3.8
Requires-Dist: openai
Requires-Dist: mcp[cli]
Requires-Dist: python-dotenv
Requires-Dist: anthropic
Requires-Dist: ollama
Requires-Dist: jsonschema
Requires-Dist: PyYAML
Requires-Dist: pdfplumber
Requires-Dist: pymupdf
Requires-Dist: openpyxl
Requires-Dist: pandas
Requires-Dist: python-docx
Requires-Dist: python-pptx
Requires-Dist: chardet
Requires-Dist: python-magic
Provides-Extra: dev
Requires-Dist: pytest; extra == "dev"
Requires-Dist: pytest-asyncio; extra == "dev"
Requires-Dist: pytest-mock; extra == "dev"
Requires-Dist: uv; extra == "dev"
Requires-Dist: build; extra == "dev"
Requires-Dist: twine; extra == "dev"
Provides-Extra: demo
Requires-Dist: mcp-server-sqlite; extra == "demo"
